AUTHOR.txt
CHANGES.txt
LICENSE.txt
README.txt
TODO.txt
bootstrap.py
buildout.cfg
setup.py
src/z3c/__init__.py
src/z3c.formjsdemo.egg-info/PKG-INFO
src/z3c.formjsdemo.egg-info/SOURCES.txt
src/z3c.formjsdemo.egg-info/dependency_links.txt
src/z3c.formjsdemo.egg-info/namespace_packages.txt
src/z3c.formjsdemo.egg-info/not-zip-safe
src/z3c.formjsdemo.egg-info/requires.txt
src/z3c.formjsdemo.egg-info/top_level.txt
src/z3c/formjsdemo/SETUP.cfg
src/z3c/formjsdemo/__init__.py
src/z3c/formjsdemo/configure.zcml
src/z3c/formjsdemo/layer.py
src/z3c/formjsdemo/browser/__init__.py
src/z3c/formjsdemo/browser/browser.py
src/z3c/formjsdemo/browser/configure.zcml
src/z3c/formjsdemo/browser/index.css
src/z3c/formjsdemo/browser/index.pt
src/z3c/formjsdemo/button/__init__.py
src/z3c/formjsdemo/button/browser.py
src/z3c/formjsdemo/button/button.css
src/z3c/formjsdemo/button/button.pt
src/z3c/formjsdemo/button/configure.zcml
src/z3c/formjsdemo/calculator/__init__.py
src/z3c/formjsdemo/calculator/browser.py
src/z3c/formjsdemo/calculator/calculator.css
src/z3c/formjsdemo/calculator/calculator.pt
src/z3c/formjsdemo/calculator/configure.zcml
src/z3c/formjsdemo/chat/__init__.py
src/z3c/formjsdemo/chat/browser.py
src/z3c/formjsdemo/chat/chat.css
src/z3c/formjsdemo/chat/chat.js
src/z3c/formjsdemo/chat/chat.pt
src/z3c/formjsdemo/chat/chat.py
src/z3c/formjsdemo/chat/configure.zcml
src/z3c/formjsdemo/chat/interfaces.py
src/z3c/formjsdemo/skin/__init__.py
src/z3c/formjsdemo/skin/configure.zcml
src/z3c/formjsdemo/skin/demo.css
src/z3c/formjsdemo/skin/demo.js
src/z3c/formjsdemo/skin/template.pt
src/z3c/formjsdemo/tree/__init__.py
src/z3c/formjsdemo/tree/browser.py
src/z3c/formjsdemo/tree/configure.zcml
src/z3c/formjsdemo/tree/contents.pt
src/z3c/formjsdemo/tree/inline.pt
src/z3c/formjsdemo/tree/interfaces.py
src/z3c/formjsdemo/tree/jquery.form.js
src/z3c/formjsdemo/tree/tree.css
src/z3c/formjsdemo/tree/tree.py
src/z3c/formjsdemo/tree/treenode.pt
src/z3c/formjsdemo/validator/__init__.py
src/z3c/formjsdemo/validator/browser.py
src/z3c/formjsdemo/validator/configure.zcml
src/z3c/formjsdemo/validator/validator.css
src/z3c/formjsdemo/validator/validator.js
src/z3c/formjsdemo/validator/validator.pt
src/z3c/formjsdemo/widgetswitch/__init__.py
src/z3c/formjsdemo/widgetswitch/browser.py
