Metadata-Version: 1.0
Name: z3c.formjsdemo
Version: 0.3.1
Summary: A set of demo applications for ``z3c.formjs``
Home-page: http://svn.zope.org/z3c.formjsdemo
Author: Paul Carduner and the Zope Community
Author-email: zope3-dev@zope.org
License: ZPL 2.1
Keywords: zope3 form widget
Platform: UNKNOWN
Classifier: Development Status :: 4 - Beta
Classifier: Environment :: Web Environment
Classifier: Intended Audience :: Developers
Classifier: License :: OSI Approved :: Zope Public License
Classifier: Programming Language :: Python
Classifier: Natural Language :: English
Classifier: Operating System :: OS Independent
Classifier: Topic :: Internet :: WWW/HTTP
Classifier: Framework :: Zope3
